matrixfun/__init__.py
matrixfun/main.py
matrixfun/multiplier.py
matrixfun-0.1.0.dist-info/METADATA
matrixfun-0.1.0.dist-info/WHEEL
matrixfun-0.1.0.dist-info/top_level.txt
matrixfun-0.1.0.dist-info/RECORD
