Metadata-Version: 2.4
Name: matrixfun
Version: 0.1.0
Summary: A humorous matrix multiplication library in Python
Author: Your Name
License: MIT
Classifier: Programming Language :: Python :: 3
Classifier: License :: OSI Approved :: MIT License
Classifier: Intended Audience :: Education
Classifier: Topic :: Scientific/Engineering :: Mathematics
Requires-Python: >=3.7
